LICENSE
README.md
setup.py
momi/__init__.py
momi/compute_sfs.py
momi/concatenate_datasets.py
momi/confidence_region.py
momi/convolution.c
momi/demo_model.py
momi/demo_plotter.py
momi/demography.py
momi/events.py
momi/extract_sfs.py
momi/likelihood.py
momi/math_functions.py
momi/moran_model.py
momi/optimizers.py
momi/read_vcf.py
momi/sfs_stats.py
momi/size_history.py
momi/util.py
momi/w_matrix.c
momi.egg-info/PKG-INFO
momi.egg-info/SOURCES.txt
momi.egg-info/dependency_links.txt
momi.egg-info/requires.txt
momi.egg-info/top_level.txt
momi/data/__init__.py
momi/data/compressed_counts.py
momi/data/configurations.py
momi/data/convert.py
momi/data/sfs.py
momi/data/snps.py
momi/data/tensor.py
momi/einsum2/__init__.py
momi/einsum2/einsum2.py
momi/einsum2/parallel_matmul.c
test/test_autograd.py
test/test_covariance.py
test/test_data_structure.py
test/test_demography.py
test/test_inference.py
test/test_likelihood.py
test/test_moran_model.py
test/test_msprime.py
test/test_new_wmatrix.py
test/test_normalizing_constant.py
test/test_rank1tensor.py
test/test_read_vcf.py
test/test_sfs.py
test/test_size_history.py
test/test_stochastic_gradient.py
test/test_subsample.py
test/test_tmrca.py