Metadata-Version: 2.4
Name: momi
Version: 2.1.21
Summary: MOran Model for Inference
Home-page: https://github.com/jackkamm/momi2
Author: Jack Kamm, Jonathan Terhorst, Richard Durbin, Yun S. Song
Author-email: jkamm@stat.berkeley.edu, terhorst@stat.berkeley.edu, yss@eecs.berkeley.edu
Keywords: population genetics,statistics,site frequency spectrum,coalescent
Requires-Python: >=3.5
License-File: LICENSE
Requires-Dist: cached_property>=1.3
Requires-Dist: autograd>=1.2.0
Requires-Dist: numpy>=1.9.0
Requires-Dist: networkx
Requires-Dist: scipy
Requires-Dist: pandas
Requires-Dist: msprime
Requires-Dist: matplotlib>=3.3
Requires-Dist: seaborn
Requires-Dist: pysam
Dynamic: author
Dynamic: author-email
Dynamic: home-page
Dynamic: keywords
Dynamic: license-file
Dynamic: requires-dist
Dynamic: requires-python
Dynamic: summary
